leap/UIE.py
leap/__init__.py
leap/config_handler.py
leap/event_handler.py
leap/generation.py
leap/generation_tf.py
leap/logging_handler.py
leap/objectives.py
leap/objectives_tf.py
leap/saliency.py
leap/saliency_tf.py
leap/transforms.py
leap/transforms_tf.py
leap/utils.py
leap/vega_charts.py
leap_temp/UIE.cpython-39-darwin.so
leap_temp/UIE.py
leap_temp/__init__.cpython-39-darwin.so
leap_temp/__init__.py
leap_temp/config_handler.cpython-39-darwin.so
leap_temp/config_handler.py
leap_temp/event_handler.cpython-39-darwin.so
leap_temp/event_handler.py
leap_temp/generation.cpython-39-darwin.so
leap_temp/generation.py
leap_temp/generation_tf.cpython-39-darwin.so
leap_temp/generation_tf.py
leap_temp/logging_handler.cpython-39-darwin.so
leap_temp/logging_handler.py
leap_temp/objectives.cpython-39-darwin.so
leap_temp/objectives.py
leap_temp/objectives_tf.cpython-39-darwin.so
leap_temp/objectives_tf.py
leap_temp/saliency.cpython-39-darwin.so
leap_temp/saliency.py
leap_temp/saliency_tf.cpython-39-darwin.so
leap_temp/saliency_tf.py
leap_temp/setup.cpython-39-darwin.so
leap_temp/setup.py
leap_temp/transforms.cpython-39-darwin.so
leap_temp/transforms.py
leap_temp/transforms_tf.cpython-39-darwin.so
leap_temp/transforms_tf.py
leap_temp/utils.cpython-39-darwin.so
leap_temp/utils.py
leap_temp/vega_charts.cpython-39-darwin.so
leap_temp/vega_charts.py
Leap_Labs-0.1.0.dist-info/METADATA
Leap_Labs-0.1.0.dist-info/WHEEL
Leap_Labs-0.1.0.dist-info/top_level.txt
Leap_Labs-0.1.0.dist-info/RECORD
